{"model_key": "dr_ping_g10", "model_label": "ピン G10", "brand": "ピン", "year": "—", "catalog": true, "mode": "single", "total_listings": 10, "used": {"count": 7, "avg": 7300, "min": 6348, "max": 8587, "median": 6980}, "flea_sold": {"count": 3, "avg": 3460, "min": 3200, "max": 3980, "median": 3200}, "gap": {"profit": -4934, "used_base": 6348, "flea_base": 3460, "basis": "min_avg", "fee_rate": 0.1, "shipping": 1700}, "mercari_hot": [], "headline": {"used_avg": 7300, "used_min": 6348, "flea_sold_avg": 3460, "gap": {"profit": -4934, "used_base": 6348, "flea_base": 3460, "basis": "min_avg", "fee_rate": 0.1, "shipping": 1700}}, "used_samples": [{"price": 6348, "title": "【中古】 ピン G10 9° ドライバー DR PROFORCE V2 HIGH LAUNCH 65 (フレックスS) メンズ 男性用 右利き 右用 Dランク ゴルフクラブ", "url": "https://item.rakuten.co.jp/golfpartner/2100413150588/?rafcid=wsc_i_is_85703369-2490-4cb5-baeb-08a443ea38ca", "shop": "ゴルフパートナー 中古クラブ店", "loft": "9", "head_only": false, "sold": false}, {"price": 6370, "title": "【中古】 ピン G10 10.5° ドライバー DR TFC 570D (フレックスR) メンズ 男性用 右利き 右用 Cランク ゴルフクラブ", "url": "https://item.rakuten.co.jp/golfpartner/2100401044080/?rafcid=wsc_i_is_85703369-2490-4cb5-baeb-08a443ea38ca", "shop": "ゴルフパートナー 中古クラブ店", "loft": "10.5", "head_only": false, "sold": false}, {"price": 6760, "title": "【中古】ピン G10 ドライバー 10.5° Sフレックス 45.0インチ USTプロフォース V2-65 HL Dランク 右利き用 PING ゴルフクラブ ゴルフドゥ ゴルフ用品 GOLF DO 中古ゴルフクラブ", "url": "https://item.rakuten.co.jp/golfdo-official/21740715601114557003/?rafcid=wsc_i_is_85703369-2490-4cb5-baeb-08a443ea38ca", "shop": "ゴルフ ドゥ 中古クラブ楽天市場店", "loft": "10.5", "head_only": false, "sold": false}, {"price": 6980, "title": "【保証付】【中古】 PING ピン G10 1W ドライバー メンズ ゴルフ クラブ ウッド 初心者 入門", "url": "https://item.rakuten.co.jp/re-next/rc_iteew0mvli8a_l8mj/?rafcid=wsc_i_is_85703369-2490-4cb5-baeb-08a443ea38ca", "shop": "リユースネクスト楽天市場店", "loft": "", "head_only": false, "sold": false}, {"price": 7467, "title": "【中古】 ピン G10 9° ドライバー DR 純正特注シャフト (フレックスS) メンズ 男性用 右利き 右用 Cランク ゴルフクラブ", "url": "https://item.rakuten.co.jp/golfpartner/2100413243082/?rafcid=wsc_i_is_85703369-2490-4cb5-baeb-08a443ea38ca", "shop": "ゴルフパートナー 中古クラブ店", "loft": "9", "head_only": false, "sold": false}, {"price": 8587, "title": "【中古】 ピン G10 10.5° ドライバー DR TFC 570D (フレックスS) メンズ 男性用 右利き 右用 Cランク ゴルフクラブ", "url": "https://item.rakuten.co.jp/golfpartner/2100419107456/?rafcid=wsc_i_is_85703369-2490-4cb5-baeb-08a443ea38ca", "shop": "ゴルフパートナー 中古クラブ店", "loft": "10.5", "head_only": false, "sold": false}, {"price": 8587, "title": "【中古】 ピン G10 7.5° ドライバー DR 純正特注シャフト (フレックスX) メンズ 男性用 右利き 右用 Cランク ゴルフクラブ", "url": "https://item.rakuten.co.jp/golfpartner/2100418735278/?rafcid=wsc_i_is_85703369-2490-4cb5-baeb-08a443ea38ca", "shop": "ゴルフパートナー 中古クラブ店", "loft": "7.5", "head_only": false, "sold": false}], "flea_samples": [{"price": 3200, "title": "DDD-2042 PING ドライバー G10 flexS ヘッドカバー付き", "url": "https://jp.mercari.com/item/m73099313039", "shop": "メルカリ販売中(最安)", "loft": "", "head_only": false, "sold": false}, {"price": 3200, "title": "PING G10 ドライバー ロフト5°", "url": "https://jp.mercari.com/item/m29978809748", "shop": "メルカリ販売中(最安)", "loft": "5", "head_only": false, "sold": false}, {"price": 3980, "title": "PING G10 ドライバー ロフト9° 45.75インチ", "url": "https://jp.mercari.com/item/m23368466797", "shop": "メルカリ売切（2025-09-18）", "loft": "9", "head_only": false, "sold": true}], "_fetched_at": "2026-07-25 00:15"}