{"model_key": "yt_driver_speed3", "model_label": "コブラ RAD SPEED", "brand": "コブラ", "year": "—", "catalog": true, "mode": "single", "total_listings": 10, "used": {"count": 7, "avg": 10804, "min": 5228, "max": 18080, "median": 7467}, "flea_sold": {"count": 3, "avg": 14133, "min": 13500, "max": 14900, "median": 14000}, "gap": {"profit": 5792, "used_base": 5228, "flea_base": 14133, "basis": "min_avg", "fee_rate": 0.1, "shipping": 1700}, "mercari_hot": [], "headline": {"used_avg": 10804, "used_min": 5228, "flea_sold_avg": 14133, "gap": {"profit": 5792, "used_base": 5228, "flea_base": 14133, "basis": "min_avg", "fee_rate": 0.1, "shipping": 1700}}, "used_samples": [{"price": 5228, "title": "【中古】 コブラ KING cobra F/SPEED LD(2008) 9.5° ドライバー DR Tour AD F/SPEED LD (フレックスS) メンズ 男性用 右利き 右用 Cランク ゴルフクラブ", "url": "https://item.rakuten.co.jp/golfpartner/2100415377877/?rafcid=wsc_i_is_85703369-2490-4cb5-baeb-08a443ea38ca", "shop": "ゴルフパートナー 中古クラブ店", "loft": "9.5", "head_only": false, "sold": false}, {"price": 6348, "title": "【中古】 コブラ KING cobra F/SPEED LD(2008) 10.5° ドライバー DR Tour AD F/SPEED LD (フレックスSR) メンズ 男性用 右利き 右用 Cランク ゴルフクラブ", "url": "https://item.rakuten.co.jp/golfpartner/2100401146296/?rafcid=wsc_i_is_85703369-2490-4cb5-baeb-08a443ea38ca", "shop": "ゴルフパートナー 中古クラブ店", "loft": "10.5", "head_only": false, "sold": false}, {"price": 6348, "title": "【中古】 コブラ KING cobra M/SPEED LD(2008) 10.5° ドライバー DR Tour AD M/SPEED LD (フレックスSR) メンズ 男性用 右利き 右用 Cランク ゴルフクラブ", "url": "https://item.rakuten.co.jp/golfpartner/2100407170677/?rafcid=wsc_i_is_85703369-2490-4cb5-baeb-08a443ea38ca", "shop": "ゴルフパートナー 中古クラブ店", "loft": "10.5", "head_only": false, "sold": false}, {"price": 7467, "title": "【中古】 コブラ KING cobra M/SPEED LD(2008) 10.5° ドライバー DR Tour AD M/SPEED LD (フレックスSR) メンズ 男性用 右利き 右用 Cランク ゴルフクラブ", "url": "https://item.rakuten.co.jp/golfpartner/2100419673111/?rafcid=wsc_i_is_85703369-2490-4cb5-baeb-08a443ea38ca", "shop": "ゴルフパートナー 中古クラブ店", "loft": "10.5", "head_only": false, "sold": false}, {"price": 16080, "title": "【中古】コブラ　KING　キング RAD SPEED ドライバー Speeder Evolution for RADSPEED　シャフト：Speeder Evolution for RADSPEEDCDランク　フレックスSR　男性用 メンズ用　右用", "url": "https://item.rakuten.co.jp/gdoshop/5003063591-001/?rafcid=wsc_i_is_85703369-2490-4cb5-baeb-08a443ea38ca", "shop": "GDOゴルフショップ 楽天市場店", "loft": "", "head_only": false, "sold": false}, {"price": 16080, "title": "【中古】コブラ　KING　キング RAD SPEED ドライバー Speeder Evolution for RADSPEED　シャフト：Speeder Evolution for RADSPEEDCDランク　フレックスS　男性用 メンズ用　右用", "url": "https://item.rakuten.co.jp/gdoshop/5003091473-001/?rafcid=wsc_i_is_85703369-2490-4cb5-baeb-08a443ea38ca", "shop": "GDOゴルフショップ 楽天市場店", "loft": "", "head_only": false, "sold": false}, {"price": 18080, "title": "【中古】コブラ　KING　キング RAD SPEED ドライバー Tour AD for RADSPEED　シャフト：Tour AD for RADSPEEDCランク　フレックスS　男性用 メンズ用　右用", "url": "https://item.rakuten.co.jp/gdoshop/5003084783-001/?rafcid=wsc_i_is_85703369-2490-4cb5-baeb-08a443ea38ca", "shop": "GDOゴルフショップ 楽天市場店", "loft": "", "head_only": false, "sold": false}], "flea_samples": [{"price": 13500, "title": "Cobra RADSPEED ドライバー 10.5度", "url": "https://jp.mercari.com/item/m20927712708", "shop": "メルカリ売切（2026-07-15）", "loft": "10.5", "head_only": false, "sold": true}, {"price": 14000, "title": "Cobra RAD SPEED ドライバー", "url": "https://jp.mercari.com/item/m84008263078", "shop": "メルカリ販売中(最安)", "loft": "", "head_only": false, "sold": false}, {"price": 14900, "title": "Cobra RADSPEED コブラ ラッドスピード ドライバー 9.0 カバー", "url": "https://jp.mercari.com/item/m24318438466", "shop": "メルカリ売切（2026-07-08）", "loft": "", "head_only": false, "sold": true}], "_fetched_at": "2026-07-25 00:33"}