{"model_key": "yt_driver_sumo2", "model_label": "ナイキ SQ SUMO2 5900", "brand": "ナイキ", "year": "—", "catalog": true, "mode": "single", "total_listings": 4, "used": {"count": 1, "avg": 7467, "min": 7467, "max": 7467, "median": 7467}, "flea_sold": {"count": 3, "avg": 7860, "min": 7000, "max": 9100, "median": 7480}, "gap": {"profit": -2093, "used_base": 7467, "flea_base": 7860, "basis": "min_avg", "fee_rate": 0.1, "shipping": 1700}, "mercari_hot": [], "headline": {"used_avg": 7467, "used_min": 7467, "flea_sold_avg": 7860, "gap": {"profit": -2093, "used_base": 7467, "flea_base": 7860, "basis": "min_avg", "fee_rate": 0.1, "shipping": 1700}}, "used_samples": [{"price": 7467, "title": "【中古】 ナイキ SasQuatch SUMO2 5900 13° レディース ドライバー DR Diamana SasQuatch (SUMO2 5900) (フレックスL) レディース 女性用 右利き 右用 Cランク ゴルフクラブ", "url": "https://item.rakuten.co.jp/golfpartner/2100420764068/?rafcid=wsc_i_is_85703369-2490-4cb5-baeb-08a443ea38ca", "shop": "ゴルフパートナー 中古クラブ店", "loft": "13", "head_only": false, "sold": false}], "flea_samples": [{"price": 7000, "title": "NIKE SQ SUMO2 5900 ドライバー メンズ　ゴルフ", "url": "https://jp.mercari.com/item/m50017753113", "shop": "メルカリ売切（2026-06-14）", "loft": "", "head_only": false, "sold": true}, {"price": 7480, "title": "ナイキ サスクワッチ SUMO2 5900 メンズ ドライバー単品 右打ち SQ", "url": "https://jp.mercari.com/item/m74526869027", "shop": "メルカリ販売中(最安)", "loft": "", "head_only": false, "sold": false}, {"price": 9100, "title": "即戦力 NIKE スクワッチ sumo2 5900 9.5 ドライバー 硬さS", "url": "https://jp.mercari.com/item/m68792623599", "shop": "メルカリ販売中(最安)", "loft": "", "head_only": false, "sold": false}], "_fetched_at": "2026-07-25 00:36"}