{"model_key": "yt_driver_tsr4", "model_label": "タイトリスト TSR4", "brand": "タイトリスト", "year": "—", "catalog": true, "mode": "single", "total_listings": 45, "used": {"count": 42, "avg": 37786, "min": 28759, "max": 62370, "median": 35230}, "flea_sold": {"count": 3, "avg": 24867, "min": 21600, "max": 28000, "median": 25000}, "gap": {"profit": -8079, "used_base": 28759, "flea_base": 24867, "basis": "min_avg", "fee_rate": 0.1, "shipping": 1700}, "mercari_hot": [], "headline": {"used_avg": 37786, "used_min": 28759, "flea_sold_avg": 24867, "gap": {"profit": -8079, "used_base": 28759, "flea_base": 24867, "basis": "min_avg", "fee_rate": 0.1, "shipping": 1700}}, "used_samples": [{"price": 28759, "title": "【中古】 タイトリスト TSR4 9° ドライバー DR TSP311 (フレックスS) メンズ 男性用 右利き 右用 Cランク ゴルフクラブ", "url": "https://item.rakuten.co.jp/golfpartner/2100401574150/?rafcid=wsc_i_is_85703369-2490-4cb5-baeb-08a443ea38ca", "shop": "ゴルフパートナー 中古クラブ店", "loft": "9", "head_only": false, "sold": false}, {"price": 30760, "title": "【中古】タイトリスト TSR4 ドライバー 9° Sフレックス 45.0インチ ヘッドカバーあり TSP-311 Cランク 右利き用 Titleist ゴルフクラブ ゴルフドゥ ゴルフ用品 GOLF DO 中古ゴルフクラブ", "url": "https://item.rakuten.co.jp/golfdo-official/21830206501195745001/?rafcid=wsc_i_is_85703369-2490-4cb5-baeb-08a443ea38ca", "shop": "ゴルフ ドゥ 中古クラブ楽天市場店", "loft": "9", "head_only": false, "sold": false}, {"price": 30769, "title": "【中古】 タイトリスト TSR4 10° ドライバー DR TSP311 (フレックスS) メンズ 男性用 右利き 右用 Cランク ゴルフクラブ", "url": "https://item.rakuten.co.jp/golfpartner/2100405750666/?rafcid=wsc_i_is_85703369-2490-4cb5-baeb-08a443ea38ca", "shop": "ゴルフパートナー 中古クラブ店", "loft": "10", "head_only": false, "sold": false}, {"price": 30988, "title": "【中古】 タイトリスト TSR4 9° ドライバー DR 純正特注シャフト (フレックスS) メンズ 男性用 右利き 右用 Cランク ゴルフクラブ", "url": "https://item.rakuten.co.jp/golfpartner/2100372832853/?rafcid=wsc_i_is_85703369-2490-4cb5-baeb-08a443ea38ca", "shop": "ゴルフパートナー 中古クラブ店", "loft": "9", "head_only": false, "sold": false}, {"price": 31760, "title": "【中古】タイトリスト TSR4 ドライバー 9° Sフレックス 45.0インチ ヘッドカバーあり TSP-311 Dランク 右利き用 Titleist ゴルフクラブ ゴルフドゥ ゴルフ用品 GOLF DO 中古ゴルフクラブ", "url": "https://item.rakuten.co.jp/golfdo-official/22330621601145448001/?rafcid=wsc_i_is_85703369-2490-4cb5-baeb-08a443ea38ca", "shop": "ゴルフ ドゥ 中古クラブ楽天市場店", "loft": "9", "head_only": false, "sold": false}, {"price": 32107, "title": "【中古】 タイトリスト TSR4 9° USA ドライバー DR TENSEI BLACK 1K 65 (フレックスS) メンズ 男性用 右利き 右用 Cランク ゴルフクラブ", "url": "https://item.rakuten.co.jp/golfpartner/2100412738022/?rafcid=wsc_i_is_85703369-2490-4cb5-baeb-08a443ea38ca", "shop": "ゴルフパートナー 中古クラブ店", "loft": "9", "head_only": false, "sold": false}, {"price": 32700, "title": "【中古】タイトリスト TSR4 ドライバー TENSEI 1K White RIP 65 10度 S", "url": "https://item.rakuten.co.jp/gemming-crown/2007010102300468/?rafcid=wsc_i_is_85703369-2490-4cb5-baeb-08a443ea38ca", "shop": "ティーエス アウトレット館", "loft": "10", "head_only": false, "sold": false}, {"price": 32760, "title": "【中古】タイトリスト TSR4 ドライバー 9° Sフレックス 45.0インチ ヘッドカバーあり TSP-311 Cランク 右利き用 Titleist ゴルフクラブ ゴルフドゥ ゴルフ用品 GOLF DO 中古ゴルフクラブ", "url": "https://item.rakuten.co.jp/golfdo-official/29930218601134901001/?rafcid=wsc_i_is_85703369-2490-4cb5-baeb-08a443ea38ca", "shop": "ゴルフ ドゥ 中古クラブ楽天市場店", "loft": "9", "head_only": false, "sold": false}, {"price": 32778, "title": "【中古】タイトリスト TSR4 ドライバー 9° Sフレックス 45.0インチ TSP-311 Cランク 右利き用 Titleist ゴルフクラブ ゴルフドゥ ゴルフ用品 GOLF DO 中古ゴルフクラブ", "url": "https://item.rakuten.co.jp/golfdo-official/21781230501160352001/?rafcid=wsc_i_is_85703369-2490-4cb5-baeb-08a443ea38ca", "shop": "ゴルフ ドゥ 中古クラブ楽天市場店", "loft": "9", "head_only": false, "sold": false}, {"price": 32800, "title": "タイトリスト ドライバー　9度　Tensei 1K Blue 55 (S) テンセイ ブルー　2022年モデル メンズ ドライバー TSR4　9.0° GH17182【大黒屋質店出品】 【中古】【送料無料】", "url": "https://item.rakuten.co.jp/auc-daikokuyah/gh17182/?rafcid=wsc_i_is_85703369-2490-4cb5-baeb-08a443ea38ca", "shop": "大黒屋質店", "loft": "9", "head_only": false, "sold": false}, {"price": 33227, "title": "【中古】 タイトリスト TSR4 10° ドライバー DR 純正特注シャフト (フレックスS) メンズ 男性用 右利き 右用 Cランク ゴルフクラブ", "url": "https://item.rakuten.co.jp/golfpartner/2100400336865/?rafcid=wsc_i_is_85703369-2490-4cb5-baeb-08a443ea38ca", "shop": "ゴルフパートナー 中古クラブ店", "loft": "10", "head_only": false, "sold": false}, {"price": 33280, "title": "【中古】タイトリスト TSR4 ドライバー 9° Sフレックス 45.25インチ ヘッドカバーあり TSP-311 Cランク 右利き用 Titleist ゴルフクラブ ゴルフドゥ ゴルフ用品 GOLF DO 中古ゴルフクラブ", "url": "https://item.rakuten.co.jp/golfdo-official/22220411501143146001/?rafcid=wsc_i_is_85703369-2490-4cb5-baeb-08a443ea38ca", "shop": "ゴルフ ドゥ 中古クラブ楽天市場店", "loft": "9", "head_only": false, "sold": false}, {"price": 33980, "title": "【中古】タイトリスト TSR4 ドライバー 10° Sフレックス 45.0インチ TSP-311 Dランク 右利き用 Titleist ゴルフクラブ ゴルフドゥ ゴルフ用品 GOLF DO 中古ゴルフクラブ", "url": "https://item.rakuten.co.jp/golfdo-official/20110530601114414001/?rafcid=wsc_i_is_85703369-2490-4cb5-baeb-08a443ea38ca", "shop": "ゴルフ ドゥ 中古クラブ楽天市場店", "loft": "10", "head_only": false, "sold": false}, {"price": 34145, "title": "【中古】 タイトリスト TSR4 10° ドライバー DR 純正特注シャフト (フレックスS) メンズ 男性用 右利き 右用 Cランク ゴルフクラブ", "url": "https://item.rakuten.co.jp/golfpartner/2100404502075/?rafcid=wsc_i_is_85703369-2490-4cb5-baeb-08a443ea38ca", "shop": "ゴルフパートナー 中古クラブ店", "loft": "10", "head_only": false, "sold": false}, {"price": 34145, "title": "【中古】 タイトリスト TSR4 9° ドライバー DR TSP311 (フレックスS) メンズ 男性用 右利き 右用 Cランク ゴルフクラブ", "url": "https://item.rakuten.co.jp/golfpartner/2100385548123/?rafcid=wsc_i_is_85703369-2490-4cb5-baeb-08a443ea38ca", "shop": "ゴルフパートナー 中古クラブ店", "loft": "9", "head_only": false, "sold": false}, {"price": 34233, "title": "【中古】タイトリスト　TSR　TSR4 ドライバー TSP311 65　シャフト：TSP311 65Cランク　フレックスS　男性用 メンズ用　右用", "url": "https://item.rakuten.co.jp/gdoshop/5002780505-001/?rafcid=wsc_i_is_85703369-2490-4cb5-baeb-08a443ea38ca", "shop": "GDOゴルフショップ 楽天市場店", "loft": "", "head_only": false, "sold": false}, {"price": 34347, "title": "【中古】 タイトリスト TSR4 9° ドライバー DR TSP311 (フレックスS) メンズ 男性用 右利き 右用 Cランク ゴルフクラブ", "url": "https://item.rakuten.co.jp/golfpartner/2100400400023/?rafcid=wsc_i_is_85703369-2490-4cb5-baeb-08a443ea38ca", "shop": "ゴルフパートナー 中古クラブ店", "loft": "9", "head_only": false, "sold": false}, {"price": 34347, "title": "【中古】 タイトリスト TSR4 10° ドライバー DR 純正特注シャフト (フレックスS) メンズ 男性用 右利き 右用 Cランク ゴルフクラブ", "url": "https://item.rakuten.co.jp/golfpartner/2100396620641/?rafcid=wsc_i_is_85703369-2490-4cb5-baeb-08a443ea38ca", "shop": "ゴルフパートナー 中古クラブ店", "loft": "10", "head_only": false, "sold": false}, {"price": 34347, "title": "【中古】 タイトリスト TSR4 9° ドライバー DR 純正特注シャフト (フレックスS) メンズ 男性用 右利き 右用 Cランク ゴルフクラブ", "url": "https://item.rakuten.co.jp/golfpartner/2100403525365/?rafcid=wsc_i_is_85703369-2490-4cb5-baeb-08a443ea38ca", "shop": "ゴルフパートナー 中古クラブ店", "loft": "9", "head_only": false, "sold": false}, {"price": 34347, "title": "【中古】 タイトリスト TSR4 9° ドライバー DR TSP311 (フレックスS) メンズ 男性用 右利き 右用 Cランク ゴルフクラブ", "url": "https://item.rakuten.co.jp/golfpartner/2100401910972/?rafcid=wsc_i_is_85703369-2490-4cb5-baeb-08a443ea38ca", "shop": "ゴルフパートナー 中古クラブ店", "loft": "9", "head_only": false, "sold": false}, {"price": 35080, "title": "【中古】タイトリスト　TSR　TSR4 ドライバー TSP310 60　シャフト：TSP310 60CDランク　フレックスS　男性用 メンズ用　右用", "url": "https://item.rakuten.co.jp/gdoshop/5002960395-001/?rafcid=wsc_i_is_85703369-2490-4cb5-baeb-08a443ea38ca", "shop": "GDOゴルフショップ 楽天市場店", "loft": "", "head_only": false, "sold": false}, {"price": 35380, "title": "【中古】タイトリスト TSR4 ドライバー 9° Sフレックス 45.0インチ ヘッドカバーあり TSP-311 Cランク 右利き用 Titleist ゴルフクラブ ゴルフドゥ ゴルフ用品 GOLF DO 中古ゴルフクラブ", "url": "https://item.rakuten.co.jp/golfdo-official/22070215601111942002/?rafcid=wsc_i_is_85703369-2490-4cb5-baeb-08a443ea38ca", "shop": "ゴルフ ドゥ 中古クラブ楽天市場店", "loft": "9", "head_only": false, "sold": false}, {"price": 35580, "title": "【中古】タイトリスト TSR4 ドライバー 9° Sフレックス 45.0インチ ヘッドカバーあり ツアーAD DI-6 Cランク 右利き用 Titleist ゴルフクラブ ゴルフドゥ ゴルフ用品 GOLF DO 中古ゴルフクラブ", "url": "https://item.rakuten.co.jp/golfdo-official/22240314601133046001/?rafcid=wsc_i_is_85703369-2490-4cb5-baeb-08a443ea38ca", "shop": "ゴルフ ドゥ 中古クラブ楽天市場店", "loft": "9", "head_only": false, "sold": false}, {"price": 36419, "title": "【中古】 Titleist TSR4 ドライバー 1W 9.0° TSP310 FLEX-S タイトリスト ゴルフクラブ 中古 C11469900", "url": "https://item.rakuten.co.jp/yasukukaeru/c11469900/?rafcid=wsc_i_is_85703369-2490-4cb5-baeb-08a443ea38ca", "shop": "ReRe(安く買えるドットコム)", "loft": "9", "head_only": false, "sold": false}, {"price": 36587, "title": "【中古】 タイトリスト TSR4 10° ドライバー DR 純正特注シャフト (フレックスS) メンズ 男性用 右利き 右用 Cランク ゴルフクラブ", "url": "https://item.rakuten.co.jp/golfpartner/2100405694380/?rafcid=wsc_i_is_85703369-2490-4cb5-baeb-08a443ea38ca", "shop": "ゴルフパートナー 中古クラブ店", "loft": "10", "head_only": false, "sold": false}, {"price": 37380, "title": "【中古】タイトリスト TSR4 ドライバー 9.0° Sフレックス 45.0インチ TSP-311 Cランク 右利き用 Titleist ゴルフクラブ ゴルフドゥ ゴルフ用品 GOLF DO 中古ゴルフクラブ", "url": "https://item.rakuten.co.jp/golfdo-official/20390430501131519001/?rafcid=wsc_i_is_85703369-2490-4cb5-baeb-08a443ea38ca", "shop": "ゴルフ ドゥ 中古クラブ楽天市場店", "loft": "9", "head_only": false, "sold": false}, {"price": 37633, "title": "【中古】タイトリスト　TSR　TSR4 ドライバー Tour AD IZ-6　シャフト：Tour AD IZ-6CDランク　フレックスS　男性用 メンズ用　右用", "url": "https://item.rakuten.co.jp/gdoshop/5002725250-001/?rafcid=wsc_i_is_85703369-2490-4cb5-baeb-08a443ea38ca", "shop": "GDOゴルフショップ 楽天市場店", "loft": "", "head_only": false, "sold": false}, {"price": 38580, "title": "【中古】タイトリスト TSR4 US ドライバー 9° Xフレックス 45.5インチ ヘッドカバーあり TENSEI 1K Black 65 Cランク 右利き用 Titleist ゴルフクラブ ゴルフドゥ ゴルフ用品 GOLF DO 中古ゴルフクラブ", "url": "https://item.rakuten.co.jp/golfdo-official/22110715601134953001/?rafcid=wsc_i_is_85703369-2490-4cb5-baeb-08a443ea38ca", "shop": "ゴルフ ドゥ 中古クラブ楽天市場店", "loft": "9", "head_only": false, "sold": false}, {"price": 38760, "title": "【中古】タイトリスト TSR4 ドライバー 9° Sフレックス 45.0インチ TSP-311 Cランク 右利き用 Titleist ゴルフクラブ ゴルフドゥ ゴルフ用品 GOLF DO 中古ゴルフクラブ", "url": "https://item.rakuten.co.jp/golfdo-official/21740617601112922030/?rafcid=wsc_i_is_85703369-2490-4cb5-baeb-08a443ea38ca", "shop": "ゴルフ ドゥ 中古クラブ楽天市場店", "loft": "9", "head_only": false, "sold": false}, {"price": 41680, "title": "【中古】タイトリスト TSR4 ドライバー 9.0° Sフレックス 45.25インチ ヘッドカバーあり TSP-311 Cランク 右利き用 Titleist ゴルフクラブ ゴルフドゥ ゴルフ用品 GOLF DO 中古ゴルフクラブ", "url": "https://item.rakuten.co.jp/golfdo-official/22340508601165025001/?rafcid=wsc_i_is_85703369-2490-4cb5-baeb-08a443ea38ca", "shop": "ゴルフ ドゥ 中古クラブ楽天市場店", "loft": "9", "head_only": false, "sold": false}, {"price": 41760, "title": "【中古】タイトリスト TSR4 ドライバー 9° Sフレックス 45.0インチ ヘッドカバーあり TSP-311 Cランク 右利き用 Titleist ゴルフクラブ ゴルフドゥ ゴルフ用品 GOLF DO 中古ゴルフクラブ", "url": "https://item.rakuten.co.jp/golfdo-official/21690607603102823001/?rafcid=wsc_i_is_85703369-2490-4cb5-baeb-08a443ea38ca", "shop": "ゴルフ ドゥ 中古クラブ楽天市場店", "loft": "9", "head_only": false, "sold": false}, {"price": 42480, "title": "【中古】タイトリスト TSR4 ドライバー 9° Sフレックス 45.25インチ ヘッドカバーあり ツアーAD DI-6 Cランク 右利き用 Titleist ゴルフクラブ ゴルフドゥ ゴルフ用品 GOLF DO 中古ゴルフクラブ", "url": "https://item.rakuten.co.jp/golfdo-official/21860721601143500001/?rafcid=wsc_i_is_85703369-2490-4cb5-baeb-08a443ea38ca", "shop": "ゴルフ ドゥ 中古クラブ楽天市場店", "loft": "9", "head_only": false, "sold": false}, {"price": 43080, "title": "【中古】タイトリスト　TSR　TSR4 ドライバー Tour AD DI-6(2020)　シャフト：Tour AD DI-6(2020)Dランク　フレックスS　男性用 メンズ用　右用", "url": "https://item.rakuten.co.jp/gdoshop/5003092757-001/?rafcid=wsc_i_is_85703369-2490-4cb5-baeb-08a443ea38ca", "shop": "GDOゴルフショップ 楽天市場店", "loft": "", "head_only": false, "sold": false}, {"price": 43580, "title": "【中古】タイトリスト TSR4 US ドライバー 9° Sフレックス 45.0インチ ヘッドカバーあり TENSEI 1K Black 65 Cランク 右利き用 Titleist ゴルフクラブ ゴルフドゥ ゴルフ用品 GOLF DO 中古ゴルフクラブ", "url": "https://item.rakuten.co.jp/golfdo-official/20760204601134253002/?rafcid=wsc_i_is_85703369-2490-4cb5-baeb-08a443ea38ca", "shop": "ゴルフ ドゥ 中古クラブ楽天市場店", "loft": "9", "head_only": false, "sold": false}, {"price": 43680, "title": "【中古】タイトリスト TSR4 ドライバー 9° Sフレックス 45.0インチ ヘッドカバーあり TSP-311 Cランク 右利き用 Titleist ゴルフクラブ ゴルフドゥ ゴルフ用品 GOLF DO 中古ゴルフクラブ", "url": "https://item.rakuten.co.jp/golfdo-official/21420102601104109001/?rafcid=wsc_i_is_85703369-2490-4cb5-baeb-08a443ea38ca", "shop": "ゴルフ ドゥ 中古クラブ楽天市場店", "loft": "9", "head_only": false, "sold": false}, {"price": 43780, "title": "【中古】タイトリスト TSR4 ドライバー 10° Xフレックス 45.0インチ ツアーAD XC-5 Cランク 右利き用 Titleist ゴルフクラブ ゴルフドゥ ゴルフ用品 GOLF DO 中古ゴルフクラブ", "url": "https://item.rakuten.co.jp/golfdo-official/21710705601110442001/?rafcid=wsc_i_is_85703369-2490-4cb5-baeb-08a443ea38ca", "shop": "ゴルフ ドゥ 中古クラブ楽天市場店", "loft": "10", "head_only": false, "sold": false}, {"price": 44225, "title": "【中古】 タイトリスト TSR4 10° ドライバー DR 純正特注シャフト (フレックスX) メンズ 男性用 右利き 右用 Cランク ゴルフクラブ", "url": "https://item.rakuten.co.jp/golfpartner/2100407920890/?rafcid=wsc_i_is_85703369-2490-4cb5-baeb-08a443ea38ca", "shop": "ゴルフパートナー 中古クラブ店", "loft": "10", "head_only": false, "sold": false}, {"price": 45080, "title": "【中古】タイトリスト　TSR　TSR4 ドライバー Tour AD DI-5　シャフト：Tour AD DI-5Cランク　フレックスS　男性用 メンズ用　右用", "url": "https://item.rakuten.co.jp/gdoshop/5002852884-001/?rafcid=wsc_i_is_85703369-2490-4cb5-baeb-08a443ea38ca", "shop": "GDOゴルフショップ 楽天市場店", "loft": "", "head_only": false, "sold": false}, {"price": 47080, "title": "【中古】タイトリスト　TSR　TSR4 ドライバー THE ATTAS V2 5　シャフト：THE ATTAS V2 5Cランク　フレックスSX　男性用 メンズ用　右用", "url": "https://item.rakuten.co.jp/gdoshop/5002986707-001/?rafcid=wsc_i_is_85703369-2490-4cb5-baeb-08a443ea38ca", "shop": "GDOゴルフショップ 楽天市場店", "loft": "", "head_only": false, "sold": false}, {"price": 49080, "title": "【中古】タイトリスト　TSR　TSR4 ドライバー Tour AD IZ-5　シャフト：Tour AD IZ-5Cランク　フレックスS　男性用 メンズ用　右用", "url": "https://item.rakuten.co.jp/gdoshop/5003078180-001/?rafcid=wsc_i_is_85703369-2490-4cb5-baeb-08a443ea38ca", "shop": "GDOゴルフショップ 楽天市場店", "loft": "", "head_only": false, "sold": false}], "flea_samples": [{"price": 21600, "title": "ダ*ー様 Titleist TSR4 ドライバー Tour AD DI-6 発泡", "url": "https://jp.mercari.com/item/m30935585066", "shop": "メルカリ売切（2026-07-06）", "loft": "", "head_only": false, "sold": true}, {"price": 25000, "title": "タイトリスト Titleist TSR4 ドライバー 8.0度 本体（S）", "url": "https://jp.mercari.com/item/m18183061829", "shop": "メルカリ販売中(最安)", "loft": "8", "head_only": false, "sold": false}, {"price": 28000, "title": "tsr4 ドライバー　9.0° ヘッドカバー付き", "url": "https://jp.mercari.com/item/m77768880048", "shop": "メルカリ売切（2026-07-10）", "loft": "9", "head_only": false, "sold": true}], "_fetched_at": "2026-07-25 00:28"}