{"model_key": "yt_iron_mizuno", "model_label": "ミズノ Mizuno Pro M-15", "brand": "ミズノ", "year": "—", "catalog": true, "mode": "single", "total_listings": 43, "used": {"count": 40, "avg": 140336, "min": 98187, "max": 179947, "median": 146246}, "flea_sold": {"count": 3, "avg": 76000, "min": 59000, "max": 89000, "median": 80000}, "gap": {"profit": -75946, "used_base": 146246, "flea_base": 80000, "basis": "median", "fee_rate": 0.1, "shipping": 1700}, "mercari_hot": [{"title": "Mizuno Pro M-15 アイアン 6本組(No.6～9、PW,GW)", "price": 80000, "url": "https://jp.mercari.com/item/m40585309988", "sold_ref": 97000, "profit": 5600, "pct": 18}], "headline": {"used_avg": 140336, "used_min": 98187, "flea_sold_avg": 76000, "gap": {"profit": -75946, "used_base": 146246, "flea_base": 80000, "basis": "median", "fee_rate": 0.1, "shipping": 1700}}, "used_samples": [{"price": 98187, "title": "【中古】 ミズノ Mizuno Pro M-15 6S アイアンセット IR 純正特注シャフト (フレックスS) メンズ 男性用 右利き 右用 Cランク ゴルフクラブ", "url": "https://item.rakuten.co.jp/golfpartner/2100418290234/?rafcid=wsc_i_is_85703369-2490-4cb5-baeb-08a443ea38ca", "shop": "ゴルフパートナー 中古クラブ店", "loft": "", "head_only": false, "sold": false}, {"price": 100426, "title": "【中古】 ミズノ Mizuno Pro M-15 6S アイアンセット IR NS PRO MODUS3 TOUR105 (フレックスS) メンズ 男性用 右利き 右用 Cランク ゴルフクラブ", "url": "https://item.rakuten.co.jp/golfpartner/2100414997465/?rafcid=wsc_i_is_85703369-2490-4cb5-baeb-08a443ea38ca", "shop": "ゴルフパートナー 中古クラブ店", "loft": "", "head_only": false, "sold": false}, {"price": 101346, "title": "【中古】 ミズノ Mizuno Pro M-15 6S アイアンセット IR 純正特注シャフト (フレックスR) メンズ 男性用 右利き 右用 Bランク ゴルフクラブ", "url": "https://item.rakuten.co.jp/golfpartner/2100402749113/?rafcid=wsc_i_is_85703369-2490-4cb5-baeb-08a443ea38ca", "shop": "ゴルフパートナー 中古クラブ店", "loft": "", "head_only": false, "sold": false}, {"price": 106780, "title": "【中古】ミズノ Mizuno Pro M-15 アイアンセット 26° Rフレックス 37.5インチ NSプロ MODUS 3 TOUR 105 Cランク 右利き用 MIZUNO ゴルフクラブ ミズノプロ ゴルフドゥ ゴルフ用品 GOLF DO 中古ゴルフクラブ", "url": "https://item.rakuten.co.jp/golfdo-official/21770608601182440001/?rafcid=wsc_i_is_85703369-2490-4cb5-baeb-08a443ea38ca", "shop": "ゴルフ ドゥ 中古クラブ楽天市場店", "loft": "26", "head_only": false, "sold": false}, {"price": 107760, "title": "【中古】ミズノ Mizuno Pro M-15 アイアンセット 26° S200フレックス 37.5インチ ダイナミックゴールド 95 Cランク 右利き用 MIZUNO ゴルフクラブ ミズノプロ ゴルフドゥ ゴルフ用品 GOLF DO 中古ゴルフ", "url": "https://item.rakuten.co.jp/golfdo-official/29930608601113221001/?rafcid=wsc_i_is_85703369-2490-4cb5-baeb-08a443ea38ca", "shop": "ゴルフ ドゥ 中古クラブ楽天市場店", "loft": "26", "head_only": false, "sold": false}, {"price": 111650, "title": "【中古】 ミズノ Mizuno Pro M-15 6S アイアンセット IR 純正特注シャフト (フレックスR) メンズ 男性用 右利き 右用 Cランク ゴルフクラブ", "url": "https://item.rakuten.co.jp/golfpartner/2100420453993/?rafcid=wsc_i_is_85703369-2490-4cb5-baeb-08a443ea38ca", "shop": "ゴルフパートナー 中古クラブ店", "loft": "", "head_only": false, "sold": false}, {"price": 112546, "title": "【中古】 ミズノ Mizuno Pro M-15 6S アイアンセット IR Dynamic Gold 95 (フレックスS) メンズ 男性用 右利き 右用 Bランク ゴルフクラブ", "url": "https://item.rakuten.co.jp/golfpartner/2100417523531/?rafcid=wsc_i_is_85703369-2490-4cb5-baeb-08a443ea38ca", "shop": "ゴルフパートナー 中古クラブ店", "loft": "", "head_only": false, "sold": false}, {"price": 112746, "title": "【中古】 ミズノ Mizuno Pro M-15 6S アイアンセット IR Dynamic Gold 95 (フレックスS) メンズ 男性用 右利き 右用 Cランク ゴルフクラブ", "url": "https://item.rakuten.co.jp/golfpartner/2100417543201/?rafcid=wsc_i_is_85703369-2490-4cb5-baeb-08a443ea38ca", "shop": "ゴルフパートナー 中古クラブ店", "loft": "", "head_only": false, "sold": false}, {"price": 112746, "title": "【中古】 ミズノ Mizuno Pro M-15 6S アイアンセット IR 純正特注シャフト (フレックスR) メンズ 男性用 右利き 右用 Bランク ゴルフクラブ", "url": "https://item.rakuten.co.jp/golfpartner/2100410114095/?rafcid=wsc_i_is_85703369-2490-4cb5-baeb-08a443ea38ca", "shop": "ゴルフパートナー 中古クラブ店", "loft": "", "head_only": false, "sold": false}, {"price": 118347, "title": "【中古】 ミズノ Mizuno Pro M-15 6S アイアンセット IR NS PRO MODUS3 TOUR105 (フレックスS) メンズ 男性用 右利き 右用 Cランク ゴルフクラブ", "url": "https://item.rakuten.co.jp/golfpartner/2100419711851/?rafcid=wsc_i_is_85703369-2490-4cb5-baeb-08a443ea38ca", "shop": "ゴルフパートナー 中古クラブ店", "loft": "", "head_only": false, "sold": false}, {"price": 121707, "title": "【中古】 ミズノ Mizuno Pro M-15 6S アイアンセット IR 純正特注シャフト (フレックスS) メンズ 男性用 右利き 右用 Cランク ゴルフクラブ", "url": "https://item.rakuten.co.jp/golfpartner/2100413017188/?rafcid=wsc_i_is_85703369-2490-4cb5-baeb-08a443ea38ca", "shop": "ゴルフパートナー 中古クラブ店", "loft": "", "head_only": false, "sold": false}, {"price": 123946, "title": "【中古】 ミズノ Mizuno Pro M-15 6S アイアンセット IR 純正特注シャフト (フレックスS) メンズ 男性用 右利き 右用 Cランク ゴルフクラブ", "url": "https://item.rakuten.co.jp/golfpartner/2100416057426/?rafcid=wsc_i_is_85703369-2490-4cb5-baeb-08a443ea38ca", "shop": "ゴルフパートナー 中古クラブ店", "loft": "", "head_only": false, "sold": false}, {"price": 123957, "title": "【中古】 ミズノ Mizuno Pro M-15 6S アイアンセット IR Dynamic Gold 95 (フレックスS) メンズ 男性用 右利き 右用 Cランク ゴルフクラブ", "url": "https://item.rakuten.co.jp/golfpartner/2100416555878/?rafcid=wsc_i_is_85703369-2490-4cb5-baeb-08a443ea38ca", "shop": "ゴルフパートナー 中古クラブ店", "loft": "", "head_only": false, "sold": false}, {"price": 125680, "title": "【中古】ミズノ Mizuno Pro M-15 アイアンセット Sフレックス 37.75インチ MCI 80 2025 Cランク 右利き用 MIZUNO ゴルフクラブ ミズノプロ ゴルフドゥ ゴルフ用品 GOLF DO 中古ゴルフクラブ", "url": "https://item.rakuten.co.jp/golfdo-official/21550312601111031001/?rafcid=wsc_i_is_85703369-2490-4cb5-baeb-08a443ea38ca", "shop": "ゴルフ ドゥ 中古クラブ楽天市場店", "loft": "", "head_only": false, "sold": false}, {"price": 128316, "title": "【中古】 ミズノ Mizuno Pro M-15 6S アイアンセット IR 純正特注シャフト (フレックスR) メンズ 男性用 右利き 右用 Cランク ゴルフクラブ", "url": "https://item.rakuten.co.jp/golfpartner/2100406518685/?rafcid=wsc_i_is_85703369-2490-4cb5-baeb-08a443ea38ca", "shop": "ゴルフパートナー 中古クラブ店", "loft": "", "head_only": false, "sold": false}, {"price": 128428, "title": "【中古】 ミズノ Mizuno Pro M-15 6S アイアンセット IR MCI 80(2025) (フレックスS) メンズ 男性用 右利き 右用 Cランク ゴルフクラブ", "url": "https://item.rakuten.co.jp/golfpartner/2100419596915/?rafcid=wsc_i_is_85703369-2490-4cb5-baeb-08a443ea38ca", "shop": "ゴルフパートナー 中古クラブ店", "loft": "", "head_only": false, "sold": false}, {"price": 135147, "title": "【中古】 ミズノ Mizuno Pro M-15 6S アイアンセット IR 純正特注シャフト (フレックスS) メンズ 男性用 右利き 右用 Cランク ゴルフクラブ", "url": "https://item.rakuten.co.jp/golfpartner/2100414555092/?rafcid=wsc_i_is_85703369-2490-4cb5-baeb-08a443ea38ca", "shop": "ゴルフパートナー 中古クラブ店", "loft": "", "head_only": false, "sold": false}, {"price": 135147, "title": "【中古】 ミズノ Mizuno Pro M-15(グレー) 6S アイアンセット IR Dynamic Gold 105 ONYX BLACK (フレックスS) メンズ 男性用 右利き 右用 Cランク ゴルフクラブ", "url": "https://item.rakuten.co.jp/golfpartner/2100419921175/?rafcid=wsc_i_is_85703369-2490-4cb5-baeb-08a443ea38ca", "shop": "ゴルフパートナー 中古クラブ店", "loft": "", "head_only": false, "sold": false}, {"price": 139639, "title": "【中古】 ミズノ Mizuno Pro M-15 6S アイアンセット IR 純正特注シャフト (フレックスS) メンズ 男性用 右利き 右用 Cランク ゴルフクラブ", "url": "https://item.rakuten.co.jp/golfpartner/2100418630405/?rafcid=wsc_i_is_85703369-2490-4cb5-baeb-08a443ea38ca", "shop": "ゴルフパートナー 中古クラブ店", "loft": "", "head_only": false, "sold": false}, {"price": 146146, "title": "【中古】 ミズノ Mizuno Pro M-15 8S アイアンセット IR MCI 80(2025) (フレックスS) メンズ 男性用 右利き 右用 Cランク ゴルフクラブ", "url": "https://item.rakuten.co.jp/golfpartner/2100417043404/?rafcid=wsc_i_is_85703369-2490-4cb5-baeb-08a443ea38ca", "shop": "ゴルフパートナー 中古クラブ店", "loft": "", "head_only": false, "sold": false}, {"price": 146347, "title": "【中古】 ミズノ Mizuno Pro M-15 6S アイアンセット IR 純正特注シャフト (フレックスS) メンズ 男性用 右利き 右用 Cランク ゴルフクラブ", "url": "https://item.rakuten.co.jp/golfpartner/2100413070572/?rafcid=wsc_i_is_85703369-2490-4cb5-baeb-08a443ea38ca", "shop": "ゴルフパートナー 中古クラブ店", "loft": "", "head_only": false, "sold": false}, {"price": 146347, "title": "【中古】 ミズノ Mizuno Pro M-15 8S アイアンセット IR Dynamic Gold 95 (フレックスS) メンズ 男性用 右利き 右用 Aランク ゴルフクラブ", "url": "https://item.rakuten.co.jp/golfpartner/2100413000227/?rafcid=wsc_i_is_85703369-2490-4cb5-baeb-08a443ea38ca", "shop": "ゴルフパートナー 中古クラブ店", "loft": "", "head_only": false, "sold": false}, {"price": 146347, "title": "【中古】 ミズノ Mizuno Pro M-15 6S アイアンセット IR MCI 80(2025) (フレックスS) メンズ 男性用 右利き 右用 Cランク ゴルフクラブ", "url": "https://item.rakuten.co.jp/golfpartner/2100415428708/?rafcid=wsc_i_is_85703369-2490-4cb5-baeb-08a443ea38ca", "shop": "ゴルフパートナー 中古クラブ店", "loft": "", "head_only": false, "sold": false}, {"price": 153068, "title": "【中古】 ミズノ Mizuno Pro M-15 8S アイアンセット IR MCI 80(2025) (フレックスS) メンズ 男性用 右利き 右用 Cランク ゴルフクラブ", "url": "https://item.rakuten.co.jp/golfpartner/2100415427503/?rafcid=wsc_i_is_85703369-2490-4cb5-baeb-08a443ea38ca", "shop": "ゴルフパートナー 中古クラブ店", "loft": "", "head_only": false, "sold": false}, {"price": 153068, "title": "【中古】 ミズノ Mizuno Pro M-15 6S アイアンセット IR 純正特注シャフト (フレックスX) メンズ 男性用 右利き 右用 Cランク ゴルフクラブ", "url": "https://item.rakuten.co.jp/golfpartner/2100417902923/?rafcid=wsc_i_is_85703369-2490-4cb5-baeb-08a443ea38ca", "shop": "ゴルフパートナー 中古クラブ店", "loft": "", "head_only": false, "sold": false}, {"price": 157457, "title": "【中古】 ミズノ Mizuno Pro M-15 6S アイアンセット IR 純正特注シャフト (フレックスR) メンズ 男性用 右利き 右用 Bランク ゴルフクラブ", "url": "https://item.rakuten.co.jp/golfpartner/2100419816396/?rafcid=wsc_i_is_85703369-2490-4cb5-baeb-08a443ea38ca", "shop": "ゴルフパートナー 中古クラブ店", "loft": "", "head_only": false, "sold": false}, {"price": 157547, "title": "【中古】 ミズノ Mizuno Pro M-15 6S アイアンセット IR 純正特注シャフト (フレックスその他) メンズ 男性用 右利き 右用 Cランク ゴルフクラブ", "url": "https://item.rakuten.co.jp/golfpartner/2100420584826/?rafcid=wsc_i_is_85703369-2490-4cb5-baeb-08a443ea38ca", "shop": "ゴルフパートナー 中古クラブ店", "loft": "", "head_only": false, "sold": false}, {"price": 157547, "title": "【中古】 ミズノ Mizuno Pro M-15 6S アイアンセット IR 純正特注シャフト (フレックスSR) メンズ 男性用 右利き 右用 Cランク ゴルフクラブ", "url": "https://item.rakuten.co.jp/golfpartner/2100410631097/?rafcid=wsc_i_is_85703369-2490-4cb5-baeb-08a443ea38ca", "shop": "ゴルフパートナー 中古クラブ店", "loft": "", "head_only": false, "sold": false}, {"price": 158667, "title": "【中古】 ミズノ Mizuno Pro M-15 6S アイアンセット IR 純正特注シャフト (フレックスS) メンズ 男性用 右利き 右用 Bランク ゴルフクラブ", "url": "https://item.rakuten.co.jp/golfpartner/2100413456505/?rafcid=wsc_i_is_85703369-2490-4cb5-baeb-08a443ea38ca", "shop": "ゴルフパートナー 中古クラブ店", "loft": "", "head_only": false, "sold": false}, {"price": 159787, "title": "【中古】 ミズノ Mizuno Pro M-15 8S アイアンセット IR 純正特注シャフト (フレックスR) メンズ 男性用 右利き 右用 Cランク ゴルフクラブ", "url": "https://item.rakuten.co.jp/golfpartner/2100416954305/?rafcid=wsc_i_is_85703369-2490-4cb5-baeb-08a443ea38ca", "shop": "ゴルフパートナー 中古クラブ店", "loft": "", "head_only": false, "sold": false}, {"price": 162026, "title": "【中古】 ミズノ Mizuno Pro M-15 6S アイアンセット IR 純正特注シャフト (フレックスその他) メンズ 男性用 右利き 右用 Bランク ゴルフクラブ", "url": "https://item.rakuten.co.jp/golfpartner/2100411106761/?rafcid=wsc_i_is_85703369-2490-4cb5-baeb-08a443ea38ca", "shop": "ゴルフパートナー 中古クラブ店", "loft": "", "head_only": false, "sold": false}, {"price": 162480, "title": "【中古】ミズノ Mizuno Pro M-15 アイアンセット 26° Rフレックス 37.5インチ OT i 75 Bランク 右利き用 MIZUNO ゴルフクラブ ミズノプロ ゴルフドゥ ゴルフ用品 GOLF DO 中古ゴルフクラブ", "url": "https://item.rakuten.co.jp/golfdo-official/21441013501105921001/?rafcid=wsc_i_is_85703369-2490-4cb5-baeb-08a443ea38ca", "shop": "ゴルフ ドゥ 中古クラブ楽天市場店", "loft": "26", "head_only": false, "sold": false}, {"price": 162946, "title": "【中古】 ミズノ Mizuno Pro M-15 8S アイアンセット IR 純正特注シャフト (フレックスS) メンズ 男性用 右利き 右用 Cランク ゴルフクラブ", "url": "https://item.rakuten.co.jp/golfpartner/2100420542451/?rafcid=wsc_i_is_85703369-2490-4cb5-baeb-08a443ea38ca", "shop": "ゴルフパートナー 中古クラブ店", "loft": "", "head_only": false, "sold": false}, {"price": 163147, "title": "【中古】 ミズノ Mizuno Pro M-15 8S アイアンセット IR 純正特注シャフト (フレックスS) メンズ 男性用 右利き 右用 Cランク ゴルフクラブ", "url": "https://item.rakuten.co.jp/golfpartner/2100420602698/?rafcid=wsc_i_is_85703369-2490-4cb5-baeb-08a443ea38ca", "shop": "ゴルフパートナー 中古クラブ店", "loft": "", "head_only": false, "sold": false}, {"price": 166508, "title": "【中古】 ミズノ Mizuno Pro M-15 6S アイアンセット IR TRAVIL IRON 85 (フレックスS) メンズ 男性用 右利き 右用 Bランク ゴルフクラブ", "url": "https://item.rakuten.co.jp/golfpartner/2100420550135/?rafcid=wsc_i_is_85703369-2490-4cb5-baeb-08a443ea38ca", "shop": "ゴルフパートナー 中古クラブ店", "loft": "", "head_only": false, "sold": false}, {"price": 168747, "title": "【中古】 ミズノ Mizuno Pro M-15 6S アイアンセット IR 純正特注シャフト (フレックスS) メンズ 男性用 右利き 右用 Cランク ゴルフクラブ", "url": "https://item.rakuten.co.jp/golfpartner/2100416580290/?rafcid=wsc_i_is_85703369-2490-4cb5-baeb-08a443ea38ca", "shop": "ゴルフパートナー 中古クラブ店", "loft": "", "head_only": false, "sold": false}, {"price": 168747, "title": "【中古】 ミズノ Mizuno Pro M-15 8S アイアンセット IR 純正特注シャフト (フレックスその他) メンズ 男性用 右利き 右用 Bランク ゴルフクラブ", "url": "https://item.rakuten.co.jp/golfpartner/2100412816812/?rafcid=wsc_i_is_85703369-2490-4cb5-baeb-08a443ea38ca", "shop": "ゴルフパートナー 中古クラブ店", "loft": "", "head_only": false, "sold": false}, {"price": 173226, "title": "【中古】 ミズノ Mizuno Pro M-15 8S アイアンセット IR 純正特注シャフト (フレックスS) メンズ 男性用 右利き 右用 Bランク ゴルフクラブ", "url": "https://item.rakuten.co.jp/golfpartner/2100415447426/?rafcid=wsc_i_is_85703369-2490-4cb5-baeb-08a443ea38ca", "shop": "ゴルフパートナー 中古クラブ店", "loft": "", "head_only": false, "sold": false}, {"price": 178828, "title": "【中古】 ミズノ Mizuno Pro M-15 8S アイアンセット IR 純正特注シャフト (フレックスS) メンズ 男性用 右利き 右用 Cランク ゴルフクラブ", "url": "https://item.rakuten.co.jp/golfpartner/2100412542544/?rafcid=wsc_i_is_85703369-2490-4cb5-baeb-08a443ea38ca", "shop": "ゴルフパートナー 中古クラブ店", "loft": "", "head_only": false, "sold": false}, {"price": 179947, "title": "【中古】 ミズノ Mizuno Pro M-15(グレー) 8S アイアンセット IR MCI 80(2025) (フレックスS) メンズ 男性用 右利き 右用 Cランク ゴルフクラブ", "url": "https://item.rakuten.co.jp/golfpartner/2100415004896/?rafcid=wsc_i_is_85703369-2490-4cb5-baeb-08a443ea38ca", "shop": "ゴルフパートナー 中古クラブ店", "loft": "", "head_only": false, "sold": false}], "flea_samples": [{"price": 59000, "title": "Mizuno Pro 225 アイアンセット 5-P 6本セット", "url": "https://jp.mercari.com/item/m81768291039", "shop": "メルカリ売切（2026-06-30）", "loft": "", "head_only": false, "sold": true}, {"price": 80000, "title": "Mizuno Pro M-15 アイアン 6本組(No.6～9、PW,GW)", "url": "https://jp.mercari.com/item/m40585309988", "shop": "メルカリ販売中(最安)", "loft": "", "head_only": false, "sold": false}, {"price": 89000, "title": "Mizuno Pro M-15 アイアンセット 6-P 5本セット", "url": "https://jp.mercari.com/item/m61060926010", "shop": "メルカリ売切（2026-06-27）", "loft": "", "head_only": false, "sold": true}], "_fetched_at": "2026-07-25 00:18"}