{"model_key": "yt_iron_zxi4", "model_label": "スリクソン ZXi4", "brand": "スリクソン", "year": "—", "catalog": true, "mode": "single", "total_listings": 54, "used": {"count": 51, "avg": 95273, "min": 67298, "max": 157345, "median": 93280}, "flea_sold": {"count": 3, "avg": 57000, "min": 47000, "max": 65000, "median": 59000}, "gap": {"profit": -41880, "used_base": 93280, "flea_base": 59000, "basis": "median", "fee_rate": 0.1, "shipping": 1700}, "mercari_hot": [], "headline": {"used_avg": 95273, "used_min": 67298, "flea_sold_avg": 57000, "gap": {"profit": -41880, "used_base": 93280, "flea_base": 59000, "basis": "median", "fee_rate": 0.1, "shipping": 1700}}, "used_samples": [{"price": 67298, "title": "【中古】 ダンロップ SRIXON ZXi4 5S アイアンセット IR 純正特注シャフト (フレックスS) メンズ 男性用 右利き 右用 Cランク ゴルフクラブ", "url": "https://item.rakuten.co.jp/golfpartner/2100397709529/?rafcid=wsc_i_is_85703369-2490-4cb5-baeb-08a443ea38ca", "shop": "ゴルフパートナー 中古クラブ店", "loft": "", "head_only": false, "sold": false}, {"price": 71186, "title": "【中古】 ダンロップ SRIXON ZXi4 5S アイアンセット IR Diamana ZXi 70 for IRON (フレックスR) メンズ 男性用 右利き 右用 Cランク ゴルフクラブ", "url": "https://item.rakuten.co.jp/golfpartner/2100406038015/?rafcid=wsc_i_is_85703369-2490-4cb5-baeb-08a443ea38ca", "shop": "ゴルフパートナー 中古クラブ店", "loft": "", "head_only": false, "sold": false}, {"price": 74250, "title": "【3980円以上で送料無料】【即納】【中古】(5本セット)ダンロップ スリクソン(SRIXON) ZXi4 アイアン 2025 NSプロ 950GH neo 6〜9.P", "url": "https://item.rakuten.co.jp/golf-kace02/2026070200980314/?rafcid=wsc_i_is_85703369-2490-4cb5-baeb-08a443ea38ca", "shop": "ゴルフエース3号店楽天市場店", "loft": "", "head_only": false, "sold": false}, {"price": 75280, "title": "【中古】ダンロップ SRIXON ZXi4 アイアンセット SRフレックス 37.0インチ Diamana ZXi for IRON Cランク 右利き用 DUNLOP ゴルフクラブ スリクソンZXi4 ゴルフドゥ ゴルフ用品 GOLF DO 中古ゴルフクラブ", "url": "https://item.rakuten.co.jp/golfdo-official/21800622601113641001/?rafcid=wsc_i_is_85703369-2490-4cb5-baeb-08a443ea38ca", "shop": "ゴルフ ドゥ 中古クラブ楽天市場店", "loft": "", "head_only": false, "sold": false}, {"price": 78945, "title": "【中古】 ダンロップ SRIXON ZXi4 5S アイアンセット IR Diamana ZXi 70 for IRON (フレックスS) メンズ 男性用 右利き 右用 Cランク ゴルフクラブ", "url": "https://item.rakuten.co.jp/golfpartner/2100406155866/?rafcid=wsc_i_is_85703369-2490-4cb5-baeb-08a443ea38ca", "shop": "ゴルフパートナー 中古クラブ店", "loft": "", "head_only": false, "sold": false}, {"price": 79148, "title": "【中古】 ダンロップ SRIXON ZXi4 7S アイアンセット IR 純正特注シャフト (フレックスSR) メンズ 男性用 右利き 右用 Cランク ゴルフクラブ", "url": "https://item.rakuten.co.jp/golfpartner/2100397023366/?rafcid=wsc_i_is_85703369-2490-4cb5-baeb-08a443ea38ca", "shop": "ゴルフパートナー 中古クラブ店", "loft": "", "head_only": false, "sold": false}, {"price": 81290, "title": "【3980円以上で送料無料】【即納】【中古】【美品】(5本セット)ダンロップ スリクソン(SRIXON) ZXi4 アイアン 2025 NSプロ MODUS3 TOUR105 DST 7〜9.P.A", "url": "https://item.rakuten.co.jp/golf-kace02/2026051900962173/?rafcid=wsc_i_is_85703369-2490-4cb5-baeb-08a443ea38ca", "shop": "ゴルフエース3号店楽天市場店", "loft": "", "head_only": false, "sold": false}, {"price": 81387, "title": "【中古】 ダンロップ SRIXON ZXi4 5S アイアンセット IR Diamana ZXi 70 for IRON (フレックスS) メンズ 男性用 右利き 右用 Cランク ゴルフクラブ", "url": "https://item.rakuten.co.jp/golfpartner/2100410361697/?rafcid=wsc_i_is_85703369-2490-4cb5-baeb-08a443ea38ca", "shop": "ゴルフパートナー 中古クラブ店", "loft": "", "head_only": false, "sold": false}, {"price": 81387, "title": "【中古】 ダンロップ SRIXON ZXi4 5S アイアンセット IR Diamana ZXi 70 for IRON (フレックスS) メンズ 男性用 右利き 右用 Cランク ゴルフクラブ", "url": "https://item.rakuten.co.jp/golfpartner/2100406558308/?rafcid=wsc_i_is_85703369-2490-4cb5-baeb-08a443ea38ca", "shop": "ゴルフパートナー 中古クラブ店", "loft": "", "head_only": false, "sold": false}, {"price": 82480, "title": "【中古】ダンロップ SRIXON ZXi4 アイアンセット 25.5° Sフレックス 37.75インチ Diamana ZXi for IRON Cランク 右利き用 DUNLOP ゴルフクラブ スリクソンZXi4 ゴルフドゥ ゴルフ用品 GOLF DO 中古ゴルフクラ", "url": "https://item.rakuten.co.jp/golfdo-official/21540607501173906002/?rafcid=wsc_i_is_85703369-2490-4cb5-baeb-08a443ea38ca", "shop": "ゴルフ ドゥ 中古クラブ楽天市場店", "loft": "25.5", "head_only": false, "sold": false}, {"price": 82480, "title": "【中古】ダンロップ SRIXON ZXi4 アイアンセット 25.5° Sフレックス 37.75インチ Diamana ZXi for IRON Cランク 右利き用 DUNLOP ゴルフクラブ スリクソンZXi4 ゴルフドゥ ゴルフ用品 GOLF DO 中古ゴルフクラ", "url": "https://item.rakuten.co.jp/golfdo-official/21540928501160740002/?rafcid=wsc_i_is_85703369-2490-4cb5-baeb-08a443ea38ca", "shop": "ゴルフ ドゥ 中古クラブ楽天市場店", "loft": "25.5", "head_only": false, "sold": false}, {"price": 82507, "title": "【中古】 ダンロップ SRIXON ZXi4 5S アイアンセット IR Diamana ZXi 70 for IRON (フレックスS) メンズ 男性用 右利き 右用 Cランク ゴルフクラブ", "url": "https://item.rakuten.co.jp/golfpartner/2100417647763/?rafcid=wsc_i_is_85703369-2490-4cb5-baeb-08a443ea38ca", "shop": "ゴルフパートナー 中古クラブ店", "loft": "", "head_only": false, "sold": false}, {"price": 82507, "title": "【中古】 ダンロップ SRIXON ZXi4 5S アイアンセット IR NS PRO 950GH neo (フレックスS) メンズ 男性用 右利き 右用 Cランク ゴルフクラブ", "url": "https://item.rakuten.co.jp/golfpartner/2100406558292/?rafcid=wsc_i_is_85703369-2490-4cb5-baeb-08a443ea38ca", "shop": "ゴルフパートナー 中古クラブ店", "loft": "", "head_only": false, "sold": false}, {"price": 84747, "title": "【中古】 ダンロップ SRIXON ZXi4 5S アイアンセット IR Diamana ZXi 70 for IRON (フレックスS) メンズ 男性用 右利き 右用 Cランク ゴルフクラブ", "url": "https://item.rakuten.co.jp/golfpartner/2100409093127/?rafcid=wsc_i_is_85703369-2490-4cb5-baeb-08a443ea38ca", "shop": "ゴルフパートナー 中古クラブ店", "loft": "", "head_only": false, "sold": false}, {"price": 86760, "title": "【中古】ダンロップ SRIXON ZXi4 アイアンセット R300フレックス 37.0インチ ダイナミックゴールド 85 Cランク 右利き用 DUNLOP ゴルフクラブ スリクソンZXi4 ゴルフドゥ ゴルフ用品 GOLF DO 中古ゴルフ", "url": "https://item.rakuten.co.jp/golfdo-official/21731220501134631001/?rafcid=wsc_i_is_85703369-2490-4cb5-baeb-08a443ea38ca", "shop": "ゴルフ ドゥ 中古クラブ楽天市場店", "loft": "", "head_only": false, "sold": false}, {"price": 88106, "title": "【中古】 ダンロップ SRIXON ZXi4 5S アイアンセット IR Diamana ZXi 70 for IRON (フレックスS) メンズ 男性用 右利き 右用 Bランク ゴルフクラブ", "url": "https://item.rakuten.co.jp/golfpartner/2100393080127/?rafcid=wsc_i_is_85703369-2490-4cb5-baeb-08a443ea38ca", "shop": "ゴルフパートナー 中古クラブ店", "loft": "", "head_only": false, "sold": false}, {"price": 88760, "title": "【中古】ダンロップ SRIXON ZXi4 アイアンセット 25.5° Sフレックス 37.5インチ NSプロ950GH neo Cランク 右利き用 DUNLOP ゴルフクラブ スリクソンZXi4 ゴルフドゥ ゴルフ用品 GOLF DO 中古ゴルフクラブ", "url": "https://item.rakuten.co.jp/golfdo-official/22291202500170708004/?rafcid=wsc_i_is_85703369-2490-4cb5-baeb-08a443ea38ca", "shop": "ゴルフ ドゥ 中古クラブ楽天市場店", "loft": "25.5", "head_only": false, "sold": false}, {"price": 90146, "title": "【中古】 ダンロップ SRIXON ZXi4 5S アイアンセット IR NS PRO 950GH neo (フレックスS) メンズ 男性用 右利き 右用 Cランク ゴルフクラブ", "url": "https://item.rakuten.co.jp/golfpartner/2100395612494/?rafcid=wsc_i_is_85703369-2490-4cb5-baeb-08a443ea38ca", "shop": "ゴルフパートナー 中古クラブ店", "loft": "", "head_only": false, "sold": false}, {"price": 90359, "title": "【中古】 ダンロップ SRIXON ZXi4 5S アイアンセット IR 純正特注シャフト (フレックスR) メンズ 男性用 右利き 右用 Cランク ゴルフクラブ", "url": "https://item.rakuten.co.jp/golfpartner/2100389358728/?rafcid=wsc_i_is_85703369-2490-4cb5-baeb-08a443ea38ca", "shop": "ゴルフパートナー 中古クラブ店", "loft": "", "head_only": false, "sold": false}, {"price": 90359, "title": "【中古】 ダンロップ SRIXON ZXi4 7S アイアンセット IR 純正特注シャフト (フレックスR) メンズ 男性用 右利き 右用 Cランク ゴルフクラブ", "url": "https://item.rakuten.co.jp/golfpartner/2100390438839/?rafcid=wsc_i_is_85703369-2490-4cb5-baeb-08a443ea38ca", "shop": "ゴルフパートナー 中古クラブ店", "loft": "", "head_only": false, "sold": false}, {"price": 90359, "title": "【中古】 ダンロップ SRIXON ZXi4 7S アイアンセット IR 純正特注シャフト (フレックスS) メンズ 男性用 右利き 右用 Cランク ゴルフクラブ", "url": "https://item.rakuten.co.jp/golfpartner/2100412932925/?rafcid=wsc_i_is_85703369-2490-4cb5-baeb-08a443ea38ca", "shop": "ゴルフパートナー 中古クラブ店", "loft": "", "head_only": false, "sold": false}, {"price": 90460, "title": "【中古】BC：ダンロップ スリクソン ZXi4アイアンセット5本（＃6-P） ロフト29° ディアマナ ZXi70/S", "url": "https://item.rakuten.co.jp/golbaka/vc4-2507-124442/?rafcid=wsc_i_is_85703369-2490-4cb5-baeb-08a443ea38ca", "shop": "ゴルフバカ一代", "loft": "29", "head_only": false, "sold": false}, {"price": 91468, "title": "【中古】 ダンロップ SRIXON ZXi4 5S アイアンセット IR 純正特注シャフト (フレックスS) メンズ 男性用 右利き 右用 Cランク ゴルフクラブ", "url": "https://item.rakuten.co.jp/golfpartner/2100406778416/?rafcid=wsc_i_is_85703369-2490-4cb5-baeb-08a443ea38ca", "shop": "ゴルフパートナー 中古クラブ店", "loft": "", "head_only": false, "sold": false}, {"price": 91760, "title": "【中古】ダンロップ SRIXON ZXi4 アイアンセット SRフレックス 37.5インチ Diamana ZXi for IRON Cランク 右利き用 DUNLOP ゴルフクラブ スリクソンZXi4 ゴルフドゥ ゴルフ用品 GOLF DO 中古ゴルフクラブ", "url": "https://item.rakuten.co.jp/golfdo-official/21930507601190537001/?rafcid=wsc_i_is_85703369-2490-4cb5-baeb-08a443ea38ca", "shop": "ゴルフ ドゥ 中古クラブ楽天市場店", "loft": "", "head_only": false, "sold": false}, {"price": 93180, "title": "【中古】ダンロップ SRIXON ZXi4 アイアンセット 25.5° Sフレックス 37.75インチ NSプロ950GH neo Cランク 右利き用 DUNLOP ゴルフクラブ スリクソンZXi4 ゴルフドゥ ゴルフ用品 GOLF DO 中古ゴルフクラブ", "url": "https://item.rakuten.co.jp/golfdo-official/21440727501115013001/?rafcid=wsc_i_is_85703369-2490-4cb5-baeb-08a443ea38ca", "shop": "ゴルフ ドゥ 中古クラブ楽天市場店", "loft": "25.5", "head_only": false, "sold": false}, {"price": 93280, "title": "【中古】 メーカー特注品 右用 ダンロップ スリクソン ZXi4 アイアン TRAVIL 95 5本セット(#6~PW) フレックスS", "url": "https://item.rakuten.co.jp/tsuruyagolf/250909-dlir-c01/?rafcid=wsc_i_is_85703369-2490-4cb5-baeb-08a443ea38ca", "shop": "つるやゴルフ楽天市場店", "loft": "", "head_only": false, "sold": false}, {"price": 93280, "title": "【07/25限定★抽選100%Pバック★要エントリー+最大10%オフCP配布中】 【中古】 メーカー特注品 右用 ダンロップ スリクソン ZXi4 アイアン TRAVIL 95 5本セット(#6~PW) フレックスS", "url": "https://item.rakuten.co.jp/jopro/250909-dlir-c01/?rafcid=wsc_i_is_85703369-2490-4cb5-baeb-08a443ea38ca", "shop": "ゴルフショップジョプロ楽天市場店", "loft": "", "head_only": false, "sold": false}, {"price": 94760, "title": "【中古】ダンロップ SRIXON ZXi4 アイアンセット Sフレックス 37.75インチ NSプロ950GH neo Bランク 右利き用 DUNLOP ゴルフクラブ スリクソンZXi4 ゴルフドゥ ゴルフ用品 GOLF DO 中古ゴルフクラブ", "url": "https://item.rakuten.co.jp/golfdo-official/21271213501145934001/?rafcid=wsc_i_is_85703369-2490-4cb5-baeb-08a443ea38ca", "shop": "ゴルフ ドゥ 中古クラブ楽天市場店", "loft": "", "head_only": false, "sold": false}, {"price": 95958, "title": "【中古】 ダンロップ SRIXON ZXi4 5S アイアンセット IR Diamana ZXi 70 for IRON (フレックスR) メンズ 男性用 右利き 右用 Cランク ゴルフクラブ", "url": "https://item.rakuten.co.jp/golfpartner/2100408556142/?rafcid=wsc_i_is_85703369-2490-4cb5-baeb-08a443ea38ca", "shop": "ゴルフパートナー 中古クラブ店", "loft": "", "head_only": false, "sold": false}, {"price": 96280, "title": "【中古】ダンロップ SRIXON ZXi4 アイアンセット Sフレックス 37.75インチ Diamana ZXi for IRON Cランク 右利き用 DUNLOP ゴルフクラブ スリクソンZXi4 ゴルフドゥ ゴルフ用品 GOLF DO 中古ゴルフクラブ", "url": "https://item.rakuten.co.jp/golfdo-official/21800504602145205001/?rafcid=wsc_i_is_85703369-2490-4cb5-baeb-08a443ea38ca", "shop": "ゴルフ ドゥ 中古クラブ楽天市場店", "loft": "", "head_only": false, "sold": false}, {"price": 97067, "title": "【中古】 ダンロップ SRIXON ZXi4 7S アイアンセット IR NS PRO 950GH neo (フレックスS) メンズ 男性用 右利き 右用 Cランク ゴルフクラブ", "url": "https://item.rakuten.co.jp/golfpartner/2100391822231/?rafcid=wsc_i_is_85703369-2490-4cb5-baeb-08a443ea38ca", "shop": "ゴルフパートナー 中古クラブ店", "loft": "", "head_only": false, "sold": false}, {"price": 97760, "title": "【中古】ダンロップ SRIXON ZXi4 アイアンセット SRフレックス 37.75インチ Diamana ZXi for IRON Cランク 右利き用 DUNLOP ゴルフクラブ スリクソンZXi4 ゴルフドゥ ゴルフ用品 GOLF DO 中古ゴルフクラブ", "url": "https://item.rakuten.co.jp/golfdo-official/22191222501124923003/?rafcid=wsc_i_is_85703369-2490-4cb5-baeb-08a443ea38ca", "shop": "ゴルフ ドゥ 中古クラブ楽天市場店", "loft": "", "head_only": false, "sold": false}, {"price": 99580, "title": "【中古】ダンロップ SRIXON ZXi4 アイアンセット Sフレックス 37.5インチ NSプロ950GH neo Bランク 右利き用 DUNLOP ゴルフクラブ スリクソンZXi4 ゴルフドゥ ゴルフ用品 GOLF DO 中古ゴルフクラブ", "url": "https://item.rakuten.co.jp/golfdo-official/22031211502154625001/?rafcid=wsc_i_is_85703369-2490-4cb5-baeb-08a443ea38ca", "shop": "ゴルフ ドゥ 中古クラブ楽天市場店", "loft": "", "head_only": false, "sold": false}, {"price": 101547, "title": "【中古】 ダンロップ SRIXON ZXi4 5S アイアンセット IR Diamana ZXi 70 for IRON (フレックスS) メンズ 男性用 右利き 右用 Cランク ゴルフクラブ", "url": "https://item.rakuten.co.jp/golfpartner/2100404337196/?rafcid=wsc_i_is_85703369-2490-4cb5-baeb-08a443ea38ca", "shop": "ゴルフパートナー 中古クラブ店", "loft": "", "head_only": false, "sold": false}, {"price": 101547, "title": "【中古】 ダンロップ SRIXON ZXi4 5S アイアンセット IR Diamana ZXi 70 for IRON (フレックスS) メンズ 男性用 右利き 右用 Cランク ゴルフクラブ", "url": "https://item.rakuten.co.jp/golfpartner/2100415708268/?rafcid=wsc_i_is_85703369-2490-4cb5-baeb-08a443ea38ca", "shop": "ゴルフパートナー 中古クラブ店", "loft": "", "head_only": false, "sold": false}, {"price": 101547, "title": "【中古】 ダンロップ SRIXON ZXi4 5S アイアンセット IR NS PRO 950GH neo (フレックスS) メンズ 男性用 右利き 右用 Cランク ゴルフクラブ", "url": "https://item.rakuten.co.jp/golfpartner/2100418268998/?rafcid=wsc_i_is_85703369-2490-4cb5-baeb-08a443ea38ca", "shop": "ゴルフパートナー 中古クラブ店", "loft": "", "head_only": false, "sold": false}, {"price": 101547, "title": "【中古】 ダンロップ SRIXON ZXi4 5S アイアンセット IR Diamana ZXi 70 for IRON (フレックスR) メンズ 男性用 右利き 右用 Cランク ゴルフクラブ", "url": "https://item.rakuten.co.jp/golfpartner/2100415995927/?rafcid=wsc_i_is_85703369-2490-4cb5-baeb-08a443ea38ca", "shop": "ゴルフパートナー 中古クラブ店", "loft": "", "head_only": false, "sold": false}, {"price": 103788, "title": "【中古】 ダンロップ SRIXON ZXi4 5S アイアンセット IR Diamana ZXi 70 for IRON (フレックスS) メンズ 男性用 右利き 右用 Cランク ゴルフクラブ", "url": "https://item.rakuten.co.jp/golfpartner/2100388124324/?rafcid=wsc_i_is_85703369-2490-4cb5-baeb-08a443ea38ca", "shop": "ゴルフパートナー 中古クラブ店", "loft": "", "head_only": false, "sold": false}, {"price": 104760, "title": "【中古】ダンロップ SRIXON ZXi4 アイアンセット 25.5° Sフレックス 37.75インチ NSプロ950GH neo Sランク 右利き用 DUNLOP ゴルフクラブ スリクソンZXi4 ゴルフドゥ ゴルフ用品 GOLF DO 中古ゴルフクラブ", "url": "https://item.rakuten.co.jp/golfdo-official/22160325504180058000/?rafcid=wsc_i_is_85703369-2490-4cb5-baeb-08a443ea38ca", "shop": "ゴルフ ドゥ 中古クラブ楽天市場店", "loft": "25.5", "head_only": false, "sold": false}, {"price": 104908, "title": "【中古】 ダンロップ SRIXON ZXi4 5S アイアンセット IR Diamana ZXi 70 for IRON (フレックスS) メンズ 男性用 右利き 右用 Cランク ゴルフクラブ", "url": "https://item.rakuten.co.jp/golfpartner/2100413141463/?rafcid=wsc_i_is_85703369-2490-4cb5-baeb-08a443ea38ca", "shop": "ゴルフパートナー 中古クラブ店", "loft": "", "head_only": false, "sold": false}], "flea_samples": [{"price": 47000, "title": "SRIXON ZXi4 アイアン 4本セット6-9 105R", "url": "https://jp.mercari.com/item/m22910758864", "shop": "メルカリ売切（2026-07-04）", "loft": "", "head_only": false, "sold": true}, {"price": 59000, "title": "SAXON ZXi4アイアン P～5番 6本", "url": "https://jp.mercari.com/item/m13434328653", "shop": "メルカリ売切（2026-06-18）", "loft": "", "head_only": false, "sold": true}, {"price": 65000, "title": "スリクソンZXi4アイアン右用5本セット#6〜P", "url": "https://jp.mercari.com/item/m84019833692", "shop": "メルカリ売切（2026-06-21）", "loft": "", "head_only": false, "sold": true}], "_fetched_at": "2026-07-25 00:21"}