{"model_key": "yt_iron_s40", "model_label": "ミズノ JPX S40 FORGED", "brand": "ミズノ", "year": "—", "catalog": true, "mode": "single", "total_listings": 20, "used": {"count": 17, "avg": 110019, "min": 82507, "max": 157780, "median": 104908}, "flea_sold": {"count": 3, "avg": 98000, "min": 89000, "max": 115000, "median": 90000}, "gap": {"profit": -25608, "used_base": 104908, "flea_base": 90000, "basis": "median", "fee_rate": 0.1, "shipping": 1700}, "mercari_hot": [], "headline": {"used_avg": 110019, "used_min": 82507, "flea_sold_avg": 98000, "gap": {"profit": -25608, "used_base": 104908, "flea_base": 90000, "basis": "median", "fee_rate": 0.1, "shipping": 1700}}, "used_samples": [{"price": 82507, "title": "【中古】 ミズノ JPX S40 FORGED 7S アイアンセット IR 純正特注シャフト (フレックスS) メンズ 男性用 右利き 右用 Bランク ゴルフクラブ", "url": "https://item.rakuten.co.jp/golfpartner/2100414951924/?rafcid=wsc_i_is_85703369-2490-4cb5-baeb-08a443ea38ca", "shop": "ゴルフパートナー 中古クラブ店", "loft": "", "head_only": false, "sold": false}, {"price": 85580, "title": "【3980円以上で送料無料】【即納】【中古】【超美品】(5本セット)ミズノ JPX S40 フォージド アイアン 2026 NSプロ 950GH neo 6〜9.P", "url": "https://item.rakuten.co.jp/golf-kace02/2026062400977276/?rafcid=wsc_i_is_85703369-2490-4cb5-baeb-08a443ea38ca", "shop": "ゴルフエース3号店楽天市場店", "loft": "", "head_only": false, "sold": false}, {"price": 98187, "title": "【中古】 ミズノ JPX S40 FORGED 7S アイアンセット IR 純正特注シャフト (フレックスS) メンズ 男性用 右利き 右用 Cランク ゴルフクラブ", "url": "https://item.rakuten.co.jp/golfpartner/2100419626810/?rafcid=wsc_i_is_85703369-2490-4cb5-baeb-08a443ea38ca", "shop": "ゴルフパートナー 中古クラブ店", "loft": "", "head_only": false, "sold": false}, {"price": 98187, "title": "【中古】 ミズノ JPX S40 FORGED 5S アイアンセット IR NS PRO 950GH neo (フレックスS) メンズ 男性用 右利き 右用 Cランク ゴルフクラブ", "url": "https://item.rakuten.co.jp/golfpartner/2100419778410/?rafcid=wsc_i_is_85703369-2490-4cb5-baeb-08a443ea38ca", "shop": "ゴルフパートナー 中古クラブ店", "loft": "", "head_only": false, "sold": false}, {"price": 99306, "title": "【中古】 ミズノ JPX S40 FORGED 5S アイアンセット IR MFUSION HT i (フレックスR) メンズ 男性用 右利き 右用 Bランク ゴルフクラブ", "url": "https://item.rakuten.co.jp/golfpartner/2100411374016/?rafcid=wsc_i_is_85703369-2490-4cb5-baeb-08a443ea38ca", "shop": "ゴルフパートナー 中古クラブ店", "loft": "", "head_only": false, "sold": false}, {"price": 100226, "title": "【中古】 ミズノ JPX S40 FORGED 5S アイアンセット IR 純正特注シャフト (フレックスS) メンズ 男性用 右利き 右用 Cランク ゴルフクラブ", "url": "https://item.rakuten.co.jp/golfpartner/2100413061044/?rafcid=wsc_i_is_85703369-2490-4cb5-baeb-08a443ea38ca", "shop": "ゴルフパートナー 中古クラブ店", "loft": "", "head_only": false, "sold": false}, {"price": 101547, "title": "【中古】 ミズノ JPX S40 FORGED 5S アイアンセット IR NS PRO 950GH neo (フレックスS) メンズ 男性用 右利き 右用 Cランク ゴルフクラブ", "url": "https://item.rakuten.co.jp/golfpartner/2100418319003/?rafcid=wsc_i_is_85703369-2490-4cb5-baeb-08a443ea38ca", "shop": "ゴルフパートナー 中古クラブ店", "loft": "", "head_only": false, "sold": false}, {"price": 101547, "title": "【中古】 ミズノ JPX S40 FORGED 5S アイアンセット IR NS PRO 950GH neo (フレックスS) メンズ 男性用 右利き 右用 Cランク ゴルフクラブ", "url": "https://item.rakuten.co.jp/golfpartner/2100418376914/?rafcid=wsc_i_is_85703369-2490-4cb5-baeb-08a443ea38ca", "shop": "ゴルフパートナー 中古クラブ店", "loft": "", "head_only": false, "sold": false}, {"price": 104908, "title": "【中古】 ミズノ JPX S40 FORGED 5S アイアンセット IR 純正特注シャフト (フレックスR) メンズ 男性用 右利き 右用 Aランク ゴルフクラブ", "url": "https://item.rakuten.co.jp/golfpartner/2100416685582/?rafcid=wsc_i_is_85703369-2490-4cb5-baeb-08a443ea38ca", "shop": "ゴルフパートナー 中古クラブ店", "loft": "", "head_only": false, "sold": false}, {"price": 105780, "title": "【中古】ミズノ JPX S40 FORGED アイアンセット 25° Sフレックス 37.75インチ NSプロ950GH neo Cランク 右利き用 MIZUNO ゴルフクラブ ゴルフドゥ ゴルフ用品 GOLF DO 中古ゴルフクラブ", "url": "https://item.rakuten.co.jp/golfdo-official/21650513601170128001/?rafcid=wsc_i_is_85703369-2490-4cb5-baeb-08a443ea38ca", "shop": "ゴルフ ドゥ 中古クラブ楽天市場店", "loft": "25", "head_only": false, "sold": false}, {"price": 111760, "title": "【中古】ミズノ JPX S40 FORGED アイアンセット Sフレックス 37.75インチ NSプロ950GH neo Bランク 右利き用 MIZUNO ゴルフクラブ ゴルフドゥ ゴルフ用品 GOLF DO 中古ゴルフクラブ", "url": "https://item.rakuten.co.jp/golfdo-official/22260607602183213004/?rafcid=wsc_i_is_85703369-2490-4cb5-baeb-08a443ea38ca", "shop": "ゴルフ ドゥ 中古クラブ楽天市場店", "loft": "", "head_only": false, "sold": false}, {"price": 112746, "title": "【中古】 ミズノ JPX S40 FORGED 5S アイアンセット IR MFUSION HT i (フレックスR) メンズ 男性用 右利き 右用 Cランク ゴルフクラブ", "url": "https://item.rakuten.co.jp/golfpartner/2100417330481/?rafcid=wsc_i_is_85703369-2490-4cb5-baeb-08a443ea38ca", "shop": "ゴルフパートナー 中古クラブ店", "loft": "", "head_only": false, "sold": false}, {"price": 116354, "title": "【中古】 ミズノ JPX S40 FORGED 7S アイアンセット IR NS PRO 950GH neo (フレックスS) メンズ 男性用 右利き 右用 Cランク ゴルフクラブ", "url": "https://item.rakuten.co.jp/golfpartner/2100419711608/?rafcid=wsc_i_is_85703369-2490-4cb5-baeb-08a443ea38ca", "shop": "ゴルフパートナー 中古クラブ店", "loft": "", "head_only": false, "sold": false}, {"price": 127780, "title": "【中古】ミズノ JPX S40 FORGED アイアンセット 25° Sフレックス 37.75インチ NSプロ950GH neo Cランク 右利き用 MIZUNO ゴルフクラブ ゴルフドゥ ゴルフ用品 GOLF DO 中古ゴルフクラブ", "url": "https://item.rakuten.co.jp/golfdo-official/21770422601133033001/?rafcid=wsc_i_is_85703369-2490-4cb5-baeb-08a443ea38ca", "shop": "ゴルフ ドゥ 中古クラブ楽天市場店", "loft": "25", "head_only": false, "sold": false}, {"price": 130980, "title": "【中古】ミズノ JPX S40 FORGED アイアンセット Sフレックス 37.5インチ MCI 70 2025 Cランク 右利き用 MIZUNO ゴルフクラブ ゴルフドゥ ゴルフ用品 GOLF DO 中古ゴルフクラブ", "url": "https://item.rakuten.co.jp/golfdo-official/21510703601132125001/?rafcid=wsc_i_is_85703369-2490-4cb5-baeb-08a443ea38ca", "shop": "ゴルフ ドゥ 中古クラブ楽天市場店", "loft": "", "head_only": false, "sold": false}, {"price": 135147, "title": "【中古】 ミズノ JPX S40 FORGED 5S アイアンセット IR NS PRO 950GH neo (フレックスS) メンズ 男性用 右利き 右用 Aランク ゴルフクラブ", "url": "https://item.rakuten.co.jp/golfpartner/2100419772050/?rafcid=wsc_i_is_85703369-2490-4cb5-baeb-08a443ea38ca", "shop": "ゴルフパートナー 中古クラブ店", "loft": "", "head_only": false, "sold": false}, {"price": 157780, "title": "【中古】ミズノ JPX S40 FORGED アイアンセット 25° Sフレックス 37.75インチ NSプロ950GH neo Sランク 右利き用 MIZUNO ゴルフクラブ ゴルフドゥ ゴルフ用品 GOLF DO 中古ゴルフクラブ", "url": "https://item.rakuten.co.jp/golfdo-official/20760616601185135002/?rafcid=wsc_i_is_85703369-2490-4cb5-baeb-08a443ea38ca", "shop": "ゴルフ ドゥ 中古クラブ楽天市場店", "loft": "25", "head_only": false, "sold": false}], "flea_samples": [{"price": 89000, "title": "MizunoJPX S40 FORGED6.7.8.9.P. 49アイアンセット", "url": "https://jp.mercari.com/item/m58672149694", "shop": "メルカリ売切（2026-05-05）", "loft": "", "head_only": false, "sold": true}, {"price": 90000, "title": "【新品・未開封】MIZUNO JPX S40 FORGED アイアン 5本セット", "url": "https://jp.mercari.com/item/m36452860199", "shop": "メルカリ売切（2026-05-09）", "loft": "", "head_only": false, "sold": true}, {"price": 115000, "title": "MIZUNO JPX S40 FORGED アイアン6本（6〜9.P.GW）", "url": "https://jp.mercari.com/item/m39611323334", "shop": "メルカリ売切（2026-03-26）", "loft": "", "head_only": false, "sold": true}], "_fetched_at": "2026-07-25 00:17"}